andeplane_pyodide_kernel/__init__.py
andeplane_pyodide_kernel/_version.py
andeplane_pyodide_kernel/app.py
andeplane_pyodide_kernel/constants.py
andeplane_pyodide_kernel/addons/__init__.py
andeplane_pyodide_kernel/addons/_base.py
andeplane_pyodide_kernel/addons/piplite.py
andeplane_pyodide_kernel/addons/pyodide.py
andeplane_pyodide_kernel/tests/__init__.py
andeplane_pyodide_kernel/tests/conftest.py
andeplane_pyodide_kernel/tests/test_metadata.py
andeplane_pyodide_kernel/tests/test_piplite.py
andeplane_pyodide_kernel/tests/test_pyodide.py
andeplane_pyodide_kernel/tests/test_repo.py
andeplane_pyodide_kernel/tests/fixtures/the_smallest_extension-0.1.0-py3-none-any.whl
andeplane_pyodide_kernel-0.0.12.data/data/share/jupyter/labextensions/andeplane-pyodide-kernel-extension/package.json
andeplane_pyodide_kernel-0.0.12.data/data/share/jupyter/labextensions/andeplane-pyodide-kernel-extension/static/568.27beb3b1d10653ee38a0.js
andeplane_pyodide_kernel-0.0.12.data/data/share/jupyter/labextensions/andeplane-pyodide-kernel-extension/static/568.27beb3b1d10653ee38a0.js.LICENSE.txt
andeplane_pyodide_kernel-0.0.12.data/data/share/jupyter/labextensions/andeplane-pyodide-kernel-extension/static/568.27beb3b1d10653ee38a0.js.map
andeplane_pyodide_kernel-0.0.12.data/data/share/jupyter/labextensions/andeplane-pyodide-kernel-extension/static/589.5110f2cd5da46107bd88.js
andeplane_pyodide_kernel-0.0.12.data/data/share/jupyter/labextensions/andeplane-pyodide-kernel-extension/static/589.5110f2cd5da46107bd88.js.LICENSE.txt
andeplane_pyodide_kernel-0.0.12.data/data/share/jupyter/labextensions/andeplane-pyodide-kernel-extension/static/589.5110f2cd5da46107bd88.js.map
andeplane_pyodide_kernel-0.0.12.data/data/share/jupyter/labextensions/andeplane-pyodide-kernel-extension/static/652.f8e7cecb2d805ad85457.js
andeplane_pyodide_kernel-0.0.12.data/data/share/jupyter/labextensions/andeplane-pyodide-kernel-extension/static/652.f8e7cecb2d805ad85457.js.map
andeplane_pyodide_kernel-0.0.12.dist-info/METADATA
andeplane_pyodide_kernel-0.0.12.dist-info/WHEEL
andeplane_pyodide_kernel-0.0.12.dist-info/entry_points.txt
andeplane_pyodide_kernel-0.0.12.dist-info/licenses/LICENSE
andeplane_pyodide_kernel-0.0.12.dist-info/RECORD
