Metadata-Version: 2.1
Name: andeplane-pyodide-kernel
Version: 0.0.12
Summary: Python kernel for JupyterLite powered by Pyodide
Project-URL: Homepage, https://jupyterlite-pyodide-kernel.readthedocs.io
Project-URL: Documentation, https://jupyterlite-pyodide-kernel.readthedocs.io
Project-URL: Source, https://github.com/jupyterlite/pyodide-kernel
Project-URL: Issues, https://github.com/jupyterlite/pyodide-kernel/issues
Project-URL: PyPI, https://pypi.org/project/jupyterlite-pyodide-kernel
Author: JupyterLite Contributors
License: BSD 3-Clause License
License-File: LICENSE
Keywords: browser,jupyter,jupyterlab,jupyterlite,notebook,pyodide
Classifier: Framework :: Jupyter
Classifier: License :: OSI Approved :: BSD License
Classifier: Programming Language :: Python
Classifier: Programming Language :: Python :: 3
Classifier: Programming Language :: Python :: 3.8
Classifier: Programming Language :: Python :: 3.9
Classifier: Programming Language :: Python :: 3.10
Classifier: Programming Language :: Python :: 3.11
Requires-Python: >=3.8
Requires-Dist: jupyterlite-core<0.2.0,>=0.1.0b22
Requires-Dist: pkginfo
Provides-Extra: dev
Requires-Dist: build; extra == 'dev'
Requires-Dist: hatch; extra == 'dev'
Requires-Dist: jupyterlab<3.6,>=3.5.3; extra == 'dev'
Provides-Extra: docs
Requires-Dist: ipywidgets<9,>=8.0; extra == 'docs'
Requires-Dist: jupyter-server-mathjax; extra == 'docs'
Requires-Dist: jupyterlab-language-pack-fr-fr; extra == 'docs'
Requires-Dist: jupyterlab-language-pack-zh-cn; extra == 'docs'
Requires-Dist: libarchive-c; extra == 'docs'
Requires-Dist: myst-parser; extra == 'docs'
Requires-Dist: pydata-sphinx-theme; extra == 'docs'
Requires-Dist: sphinx-copybutton; extra == 'docs'
Provides-Extra: lint
Requires-Dist: black; extra == 'lint'
Requires-Dist: ruff; extra == 'lint'
Provides-Extra: test
Requires-Dist: pytest; extra == 'test'
Requires-Dist: pytest-console-scripts; extra == 'test'
Requires-Dist: pytest-cov; extra == 'test'
Requires-Dist: pytest-html; extra == 'test'
